<?xml version="1.0"?>
<ArrayOfBusinessCardModel xmlns:xsi="http://www.w3.org/2001/XMLSchema-instance" xmlns:xsd="http://www.w3.org/2001/XMLSchema">
  <BusinessCardModel>
    <FirstName>Herrsod</FirstName>
    <LastName>RuthDunn</LastName>
    <Position>Inst</Position>
    <Department>Dep</Department>
    <PhoneNumber>123</PhoneNumber>
    <MobileNumber>456</MobileNumber>
    <Fax>789</Fax>
    <OfficeAddress>Address1</OfficeAddress>
    <Description>Apraksts</Description>
    <BossId>25</BossId>
    <Id>1</Id>
    <Email>emial@emiala.com</Email>
    <Url>https://www.facebook.com/video.php?v=10152845610968110</Url>
  </BusinessCardModel>
  <BusinessCardModel>
    <FirstName>Oren</FirstName>
    <LastName>фывафывафыв</LastName>
    <Position>Institute</Position>
    <Department>фывафыва</Department>
    <BossId>40</BossId>
    <Id>2</Id>
  </BusinessCardModel>
  <BusinessCardModel>
    <FirstName>Theodore</FirstName>
    <LastName>Holly Guerrero</LastName>
    <Position>Nunc LLC</Position>
    <BossId>0</BossId>
    <Id>3</Id>
  </BusinessCardModel>
  <BusinessCardModel>
    <FirstName>Channing</FirstName>
    <LastName>Delilah Gates</LastName>
    <Position>Fermentum Metus Aenean Incorporated</Position>
    <BossId>0</BossId>
    <Id>4</Id>
  </BusinessCardModel>
  <BusinessCardModel>
    <FirstName>Rashad</FirstName>
    <LastName>Amela Small</LastName>
    <Position>Eu Metus Consulting</Position>
    <BossId>0</BossId>
    <Id>5</Id>
  </BusinessCardModel>
  <BusinessCardModel>
    <FirstName>Ryan</FirstName>
    <LastName>Ingrid Mcintyre</LastName>
    <Position>Egestas Institute</Position>
    <BossId>0</BossId>
    <Id>6</Id>
  </BusinessCardModel>
  <BusinessCardModel>
    <FirstName>Hall</FirstName>
    <LastName>Chanda Wyatt</LastName>
    <Position>Egestas Rhoncus Proin Incorporated</Position>
    <BossId>0</BossId>
    <Id>7</Id>
  </BusinessCardModel>
  <BusinessCardModel>
    <FirstName>Reed</FirstName>
    <LastName>Jeanette Jacobs</LastName>
    <Position>Justo Faucibus Lectus Incorporated</Position>
    <BossId>0</BossId>
    <Id>8</Id>
  </BusinessCardModel>
  <BusinessCardModel>
    <FirstName>Sylvester</FirstName>
    <LastName>Hanna Rowland</LastName>
    <Position>Turpis In Limited</Position>
    <BossId>0</BossId>
    <Id>9</Id>
  </BusinessCardModel>
  <BusinessCardModel>
    <FirstName>Berk</FirstName>
    <LastName>Ciara Nichols</LastName>
    <Position>Dolor PC</Position>
    <BossId>0</BossId>
    <Id>10</Id>
  </BusinessCardModel>
  <BusinessCardModel>
    <FirstName>Kermit</FirstName>
    <LastName>Nora Mcmillan</LastName>
    <Position>Eu Metus Corporation</Position>
    <BossId>0</BossId>
    <Id>11</Id>
  </BusinessCardModel>
  <BusinessCardModel>
    <FirstName>Travis</FirstName>
    <LastName>Margaret Norman</LastName>
    <Position>Tellus Justo Sit Company</Position>
    <BossId>0</BossId>
    <Id>12</Id>
  </BusinessCardModel>
  <BusinessCardModel>
    <FirstName>Thaddeus</FirstName>
    <LastName>Mona Rice</LastName>
    <Position>Ipsum Consulting</Position>
    <BossId>0</BossId>
    <Id>13</Id>
  </BusinessCardModel>
  <BusinessCardModel>
    <FirstName>Harlan</FirstName>
    <LastName>Regina Nelson</LastName>
    <Position>Auctor Ullamcorper LLC</Position>
    <BossId>0</BossId>
    <Id>14</Id>
  </BusinessCardModel>
  <BusinessCardModel>
    <FirstName>Craig</FirstName>
    <LastName>Kitra Cooke</LastName>
    <Position>Dui Institute</Position>
    <BossId>0</BossId>
    <Id>15</Id>
  </BusinessCardModel>
  <BusinessCardModel>
    <FirstName>Upton</FirstName>
    <LastName>Mari Allen</LastName>
    <Position>Tempus Corporation</Position>
    <BossId>0</BossId>
    <Id>16</Id>
  </BusinessCardModel>
  <BusinessCardModel>
    <FirstName>David</FirstName>
    <LastName>Aretha Wynn</LastName>
    <Position>Placerat Cras Consulting</Position>
    <BossId>0</BossId>
    <Id>17</Id>
  </BusinessCardModel>
  <BusinessCardModel>
    <FirstName>Jack</FirstName>
    <LastName>Serena Boyer</LastName>
    <Position>Rutrum Consulting</Position>
    <BossId>0</BossId>
    <Id>18</Id>
  </BusinessCardModel>
  <BusinessCardModel>
    <FirstName>Talon</FirstName>
    <LastName>Melinda Stephenson</LastName>
    <Position>Ac PC</Position>
    <BossId>0</BossId>
    <Id>19</Id>
  </BusinessCardModel>
  <BusinessCardModel>
    <FirstName>Fulton</FirstName>
    <LastName>Maia Haley</LastName>
    <Position>Odio PC</Position>
    <BossId>0</BossId>
    <Id>20</Id>
  </BusinessCardModel>
  <BusinessCardModel>
    <FirstName>Drake</FirstName>
    <LastName>Dacey Elliott</LastName>
    <Position>Sapien Molestie Foundation</Position>
    <BossId>0</BossId>
    <Id>21</Id>
  </BusinessCardModel>
  <BusinessCardModel>
    <FirstName>Kadeem</FirstName>
    <LastName>Lesley Elliott</LastName>
    <Position>Sed Consulting</Position>
    <BossId>0</BossId>
    <Id>22</Id>
  </BusinessCardModel>
  <BusinessCardModel>
    <FirstName>Alvin</FirstName>
    <LastName>Danielle Santiago</LastName>
    <Position>Vitae Sodales Nisi Inc.</Position>
    <BossId>0</BossId>
    <Id>23</Id>
  </BusinessCardModel>
  <BusinessCardModel>
    <FirstName>Holmes</FirstName>
    <LastName>Nerea Ramsey</LastName>
    <Position>Elementum Sem Vitae Associates</Position>
    <BossId>0</BossId>
    <Id>24</Id>
  </BusinessCardModel>
  <BusinessCardModel>
    <FirstName>Cameron</FirstName>
    <LastName>Jolie Hays</LastName>
    <Position>Nibh LLP</Position>
    <BossId>0</BossId>
    <Id>25</Id>
  </BusinessCardModel>
  <BusinessCardModel>
    <FirstName>Reece</FirstName>
    <LastName>Orla Roach</LastName>
    <Position>Ut Tincidunt Orci Institute</Position>
    <BossId>0</BossId>
    <Id>26</Id>
  </BusinessCardModel>
  <BusinessCardModel>
    <FirstName>Donovan</FirstName>
    <LastName>Emma Walton</LastName>
    <Position>Praesent LLP</Position>
    <BossId>0</BossId>
    <Id>27</Id>
  </BusinessCardModel>
  <BusinessCardModel>
    <FirstName>Dale</FirstName>
    <LastName>Cheyenne Walters</LastName>
    <Position>Enim Ltd</Position>
    <BossId>0</BossId>
    <Id>28</Id>
  </BusinessCardModel>
  <BusinessCardModel>
    <FirstName>Dominic</FirstName>
    <LastName>Mikayla Vincent</LastName>
    <Position>Massa LLC</Position>
    <BossId>0</BossId>
    <Id>29</Id>
  </BusinessCardModel>
  <BusinessCardModel>
    <FirstName>Stuart</FirstName>
    <LastName>Gisela Reilly</LastName>
    <Position>Et Ltd</Position>
    <BossId>0</BossId>
    <Id>30</Id>
  </BusinessCardModel>
  <BusinessCardModel>
    <FirstName>Channing</FirstName>
    <LastName>Hayfa Calderon</LastName>
    <Position>Tortor Industries</Position>
    <BossId>0</BossId>
    <Id>31</Id>
  </BusinessCardModel>
  <BusinessCardModel>
    <FirstName>Zephania</FirstName>
    <LastName>Joelle Bernard</LastName>
    <Position>Enim Consequat Associates</Position>
    <BossId>0</BossId>
    <Id>32</Id>
  </BusinessCardModel>
  <BusinessCardModel>
    <FirstName>Coby</FirstName>
    <LastName>Lacey Ortega</LastName>
    <Position>Semper Company</Position>
    <BossId>0</BossId>
    <Id>33</Id>
  </BusinessCardModel>
  <BusinessCardModel>
    <FirstName>Craig</FirstName>
    <LastName>Odette Nelson</LastName>
    <Position>Vitae Orci Phasellus Corporation</Position>
    <BossId>0</BossId>
    <Id>34</Id>
  </BusinessCardModel>
  <BusinessCardModel>
    <FirstName>Chase</FirstName>
    <LastName>Amena Henry</LastName>
    <Position>Eget Ipsum Suspendisse Associates</Position>
    <BossId>0</BossId>
    <Id>35</Id>
  </BusinessCardModel>
  <BusinessCardModel>
    <FirstName>Reed</FirstName>
    <LastName>Macey Lester</LastName>
    <Position>Adipiscing Foundation</Position>
    <BossId>0</BossId>
    <Id>36</Id>
  </BusinessCardModel>
  <BusinessCardModel>
    <FirstName>Keane</FirstName>
    <LastName>Eve Wood</LastName>
    <Position>Tellus Lorem Eu Foundation</Position>
    <BossId>0</BossId>
    <Id>37</Id>
  </BusinessCardModel>
  <BusinessCardModel>
    <FirstName>Walker</FirstName>
    <LastName>Jolene Barber</LastName>
    <Position>Aliquam Corp.</Position>
    <BossId>0</BossId>
    <Id>38</Id>
  </BusinessCardModel>
  <BusinessCardModel>
    <FirstName>Leonard</FirstName>
    <LastName>Guinevere Young</LastName>
    <Position>Ligula Aliquam Erat Consulting</Position>
    <BossId>0</BossId>
    <Id>39</Id>
  </BusinessCardModel>
  <BusinessCardModel>
    <FirstName>Ashton</FirstName>
    <LastName>Lila Holt</LastName>
    <Position>Quisque Inc.</Position>
    <BossId>0</BossId>
    <Id>40</Id>
  </BusinessCardModel>
  <BusinessCardModel>
    <FirstName>Dalton</FirstName>
    <LastName>Leslie Knapp</LastName>
    <Position>Vivamus Foundation</Position>
    <BossId>0</BossId>
    <Id>41</Id>
  </BusinessCardModel>
  <BusinessCardModel>
    <FirstName>Walker</FirstName>
    <LastName>Cherokee Bryant</LastName>
    <Position>Massa Vestibulum Accumsan Corporation</Position>
    <BossId>0</BossId>
    <Id>42</Id>
  </BusinessCardModel>
  <BusinessCardModel>
    <FirstName>Allen</FirstName>
    <LastName>Cassandra Hernandez</LastName>
    <Position>Imperdiet Consulting</Position>
    <BossId>0</BossId>
    <Id>43</Id>
  </BusinessCardModel>
  <BusinessCardModel>
    <FirstName>Jonas</FirstName>
    <LastName>Cheyenne Castro</LastName>
    <Position>Est Tempor LLP</Position>
    <BossId>0</BossId>
    <Id>44</Id>
  </BusinessCardModel>
  <BusinessCardModel>
    <FirstName>Moses</FirstName>
    <LastName>Ann Tillman</LastName>
    <Position>Consequat Enim Diam Industries</Position>
    <BossId>0</BossId>
    <Id>45</Id>
  </BusinessCardModel>
  <BusinessCardModel>
    <FirstName>Raja</FirstName>
    <LastName>Bryar Lester</LastName>
    <Position>Magnis Foundation</Position>
    <BossId>0</BossId>
    <Id>46</Id>
  </BusinessCardModel>
  <BusinessCardModel>
    <FirstName>Declan</FirstName>
    <LastName>Ruth Golden</LastName>
    <Position>Per Conubia Corporation</Position>
    <BossId>0</BossId>
    <Id>47</Id>
  </BusinessCardModel>
  <BusinessCardModel>
    <FirstName>Brennan</FirstName>
    <LastName>Freya Meyers</LastName>
    <Position>Ultricies Dignissim Associates</Position>
    <BossId>0</BossId>
    <Id>48</Id>
  </BusinessCardModel>
  <BusinessCardModel>
    <FirstName>Rogan</FirstName>
    <LastName>Cally Parks</LastName>
    <Position>Eu Nulla Associates</Position>
    <BossId>0</BossId>
    <Id>49</Id>
  </BusinessCardModel>
  <BusinessCardModel>
    <FirstName>Armando</FirstName>
    <LastName>Jordan Hunter</LastName>
    <Position>Libero Morbi Accumsan Institute</Position>
    <BossId>0</BossId>
    <Id>50</Id>
  </BusinessCardModel>
  <BusinessCardModel>
    <FirstName>Yoshio</FirstName>
    <LastName>Shelley Garner</LastName>
    <Position>Lacus Mauris Company</Position>
    <BossId>0</BossId>
    <Id>51</Id>
  </BusinessCardModel>
  <BusinessCardModel>
    <FirstName>Simon</FirstName>
    <LastName>Shelley Vega</LastName>
    <Position>Pharetra Company</Position>
    <BossId>0</BossId>
    <Id>52</Id>
  </BusinessCardModel>
  <BusinessCardModel>
    <FirstName>Quamar</FirstName>
    <LastName>Ariana West</LastName>
    <Position>Amet Foundation</Position>
    <BossId>0</BossId>
    <Id>53</Id>
  </BusinessCardModel>
  <BusinessCardModel>
    <FirstName>Nero</FirstName>
    <LastName>Aspen Park</LastName>
    <Position>Nullam Ut Nisi Incorporated</Position>
    <BossId>0</BossId>
    <Id>54</Id>
  </BusinessCardModel>
  <BusinessCardModel>
    <FirstName>Brendan</FirstName>
    <LastName>Tatyana Cain</LastName>
    <Position>Nunc Interdum Feugiat Corp.</Position>
    <BossId>0</BossId>
    <Id>55</Id>
  </BusinessCardModel>
  <BusinessCardModel>
    <FirstName>Hilel</FirstName>
    <LastName>Kiona Sellers</LastName>
    <Position>Purus Ac Tellus Foundation</Position>
    <BossId>0</BossId>
    <Id>56</Id>
  </BusinessCardModel>
  <BusinessCardModel>
    <FirstName>Palmer</FirstName>
    <LastName>Shelly Valentine</LastName>
    <Position>Auctor Inc.</Position>
    <BossId>0</BossId>
    <Id>57</Id>
  </BusinessCardModel>
  <BusinessCardModel>
    <FirstName>Octavius</FirstName>
    <LastName>Harriet Hubbard</LastName>
    <Position>Sed Institute</Position>
    <BossId>0</BossId>
    <Id>58</Id>
  </BusinessCardModel>
  <BusinessCardModel>
    <FirstName>Axel</FirstName>
    <LastName>Regan Barry</LastName>
    <Position>Et Incorporated</Position>
    <BossId>0</BossId>
    <Id>59</Id>
  </BusinessCardModel>
  <BusinessCardModel>
    <FirstName>Timothy</FirstName>
    <LastName>Lara Martinez</LastName>
    <Position>Sapien Nunc Associates</Position>
    <BossId>0</BossId>
    <Id>60</Id>
  </BusinessCardModel>
  <BusinessCardModel>
    <FirstName>Damian</FirstName>
    <LastName>Basia Ashley</LastName>
    <Position>In LLC</Position>
    <BossId>0</BossId>
    <Id>61</Id>
  </BusinessCardModel>
  <BusinessCardModel>
    <FirstName>Gil</FirstName>
    <LastName>Ina Giles</LastName>
    <Position>Ante Ipsum Primis Foundation</Position>
    <BossId>0</BossId>
    <Id>62</Id>
  </BusinessCardModel>
  <BusinessCardModel>
    <FirstName>Kamal</FirstName>
    <LastName>Brenna Odom</LastName>
    <Position>Dolor Vitae Dolor Company</Position>
    <BossId>0</BossId>
    <Id>63</Id>
  </BusinessCardModel>
  <BusinessCardModel>
    <FirstName>Tanner</FirstName>
    <LastName>Sage Lynch</LastName>
    <Position>Lobortis Class Industries</Position>
    <BossId>0</BossId>
    <Id>64</Id>
  </BusinessCardModel>
  <BusinessCardModel>
    <FirstName>Steven</FirstName>
    <LastName>Kylan Wilkinson</LastName>
    <Position>Urna Convallis Foundation</Position>
    <BossId>0</BossId>
    <Id>65</Id>
  </BusinessCardModel>
  <BusinessCardModel>
    <FirstName>Gabriel</FirstName>
    <LastName>Noelani Cook</LastName>
    <Position>Non Inc.</Position>
    <BossId>0</BossId>
    <Id>66</Id>
  </BusinessCardModel>
  <BusinessCardModel>
    <FirstName>Leonard</FirstName>
    <LastName>Penelope Gamble</LastName>
    <Position>Consectetuer Corp.</Position>
    <BossId>0</BossId>
    <Id>67</Id>
  </BusinessCardModel>
  <BusinessCardModel>
    <FirstName>Cruz</FirstName>
    <LastName>Gemma Bryan</LastName>
    <Position>Porttitor Tellus Inc.</Position>
    <BossId>0</BossId>
    <Id>68</Id>
  </BusinessCardModel>
  <BusinessCardModel>
    <FirstName>Adam</FirstName>
    <LastName>шейк</LastName>
    <Position>Pharetra PC</Position>
    <Department>dep</Department>
    <BossId xsi:nil="true" />
    <Id>69</Id>
  </BusinessCardModel>
  <BusinessCardModel>
    <FirstName>Kelly</FirstName>
    <LastName>Aspen Dawson</LastName>
    <Position>Nulla Vulputate Dui Foundation</Position>
    <BossId>0</BossId>
    <Id>70</Id>
  </BusinessCardModel>
  <BusinessCardModel>
    <FirstName>Jakeem</FirstName>
    <LastName>Jael Howe</LastName>
    <Position>Nunc LLC</Position>
    <BossId>0</BossId>
    <Id>71</Id>
  </BusinessCardModel>
  <BusinessCardModel>
    <FirstName>Eaton</FirstName>
    <LastName>TaShya Washington</LastName>
    <Position>Nulla Integer Industries</Position>
    <BossId>0</BossId>
    <Id>72</Id>
  </BusinessCardModel>
  <BusinessCardModel>
    <FirstName>Denton</FirstName>
    <LastName>Leslie Humphrey</LastName>
    <Position>Nulla Aliquet Incorporated</Position>
    <BossId>0</BossId>
    <Id>73</Id>
  </BusinessCardModel>
  <BusinessCardModel>
    <FirstName>Murphy</FirstName>
    <LastName>Desirae Buck</LastName>
    <Position>Sed Pede Nec LLP</Position>
    <BossId>0</BossId>
    <Id>74</Id>
  </BusinessCardModel>
  <BusinessCardModel>
    <FirstName>Ethan</FirstName>
    <LastName>Jacqueline Welch</LastName>
    <Position>Odio Nam Interdum Corp.</Position>
    <BossId>0</BossId>
    <Id>75</Id>
  </BusinessCardModel>
  <BusinessCardModel>
    <FirstName>Austin</FirstName>
    <LastName>Audra Carlson</LastName>
    <Position>Ultrices Sit Amet PC</Position>
    <BossId>0</BossId>
    <Id>76</Id>
  </BusinessCardModel>
  <BusinessCardModel>
    <FirstName>Elvis</FirstName>
    <LastName>Adara Fletcher</LastName>
    <Position>Amet Metus Industries</Position>
    <BossId>0</BossId>
    <Id>77</Id>
  </BusinessCardModel>
  <BusinessCardModel>
    <FirstName>Jamal</FirstName>
    <LastName>Nerea Mcmahon</LastName>
    <Position>Diam Proin Dolor Foundation</Position>
    <BossId>0</BossId>
    <Id>78</Id>
  </BusinessCardModel>
  <BusinessCardModel>
    <FirstName>Reese</FirstName>
    <LastName>Irene Cain</LastName>
    <Position>Sit Amet Lorem Corp.</Position>
    <BossId>0</BossId>
    <Id>79</Id>
  </BusinessCardModel>
  <BusinessCardModel>
    <FirstName>Kenneth</FirstName>
    <LastName>Leilani Barr</LastName>
    <Position>Eu Dolor Egestas Corp.</Position>
    <BossId>0</BossId>
    <Id>80</Id>
  </BusinessCardModel>
  <BusinessCardModel>
    <FirstName>Tanek</FirstName>
    <LastName>Mollie Britt</LastName>
    <Position>Ipsum Dolor Sit LLC</Position>
    <BossId>0</BossId>
    <Id>81</Id>
  </BusinessCardModel>
  <BusinessCardModel>
    <FirstName>Ethan</FirstName>
    <LastName>Mari Stokes</LastName>
    <Position>Ipsum Curabitur LLC</Position>
    <BossId>0</BossId>
    <Id>82</Id>
  </BusinessCardModel>
  <BusinessCardModel>
    <FirstName>Martin</FirstName>
    <LastName>Kiayada Fisher</LastName>
    <Position>A Associates</Position>
    <BossId>0</BossId>
    <Id>83</Id>
  </BusinessCardModel>
  <BusinessCardModel>
    <FirstName>Hedley</FirstName>
    <LastName>Kirsten Holden</LastName>
    <Position>Enim Gravida Sit Company</Position>
    <BossId>0</BossId>
    <Id>84</Id>
  </BusinessCardModel>
  <BusinessCardModel>
    <FirstName>Keane</FirstName>
    <LastName>Hannah Shepherd</LastName>
    <Position>Lacus Pede Institute</Position>
    <BossId>0</BossId>
    <Id>85</Id>
  </BusinessCardModel>
  <BusinessCardModel>
    <FirstName>Brennan</FirstName>
    <LastName>Jolie Conner</LastName>
    <Position>Habitant Morbi Limited</Position>
    <BossId>0</BossId>
    <Id>86</Id>
  </BusinessCardModel>
  <BusinessCardModel>
    <FirstName>Lyle</FirstName>
    <LastName>Aspen Blake</LastName>
    <Position>Dignissim Limited</Position>
    <BossId>0</BossId>
    <Id>87</Id>
  </BusinessCardModel>
  <BusinessCardModel>
    <FirstName>Garrison</FirstName>
    <LastName>Uta Workman</LastName>
    <Position>Turpis LLC</Position>
    <BossId>0</BossId>
    <Id>88</Id>
  </BusinessCardModel>
  <BusinessCardModel>
    <FirstName>Fulton</FirstName>
    <LastName>Quon Watson</LastName>
    <Position>Vitae Diam Ltd</Position>
    <BossId>0</BossId>
    <Id>89</Id>
  </BusinessCardModel>
  <BusinessCardModel>
    <FirstName>Benjamin</FirstName>
    <LastName>Bree Bray</LastName>
    <Position>Dignissim Tempor Arcu LLP</Position>
    <BossId>0</BossId>
    <Id>90</Id>
  </BusinessCardModel>
  <BusinessCardModel>
    <FirstName>Mason</FirstName>
    <LastName>Roary Jenkins</LastName>
    <Position>Sed Id Consulting</Position>
    <BossId>0</BossId>
    <Id>91</Id>
  </BusinessCardModel>
  <BusinessCardModel>
    <FirstName>Dexter</FirstName>
    <LastName>Nora Charles</LastName>
    <Position>Nulla Tempor Augue Consulting</Position>
    <BossId>0</BossId>
    <Id>92</Id>
  </BusinessCardModel>
  <BusinessCardModel>
    <FirstName>Quinlan</FirstName>
    <LastName>Colette Burris</LastName>
    <Position>Ornare Corp.</Position>
    <BossId>0</BossId>
    <Id>93</Id>
  </BusinessCardModel>
  <BusinessCardModel>
    <FirstName>Henry</FirstName>
    <LastName>Idona Barber</LastName>
    <Position>Gravida Associates</Position>
    <BossId>0</BossId>
    <Id>94</Id>
  </BusinessCardModel>
  <BusinessCardModel>
    <FirstName>Uriah</FirstName>
    <LastName>Lilah Winters</LastName>
    <Position>Integer Tincidunt Industries</Position>
    <BossId>0</BossId>
    <Id>95</Id>
  </BusinessCardModel>
  <BusinessCardModel>
    <FirstName>Nasim</FirstName>
    <LastName>Shannon Hull</LastName>
    <Position>Mi Fringilla LLC</Position>
    <BossId>0</BossId>
    <Id>96</Id>
  </BusinessCardModel>
  <BusinessCardModel>
    <FirstName>Herrod</FirstName>
    <LastName>Patricia Glenn</LastName>
    <Position>Molestie In Tempus Company</Position>
    <BossId>0</BossId>
    <Id>97</Id>
  </BusinessCardModel>
  <BusinessCardModel>
    <FirstName>Conan</FirstName>
    <LastName>Brenna Battle</LastName>
    <Position>Tellus Aenean Egestas Industries</Position>
    <BossId>0</BossId>
    <Id>98</Id>
  </BusinessCardModel>
  <BusinessCardModel>
    <FirstName>Damian</FirstName>
    <LastName>Maryam Bender</LastName>
    <Position>Rutrum Corp.</Position>
    <BossId>0</BossId>
    <Id>99</Id>
  </BusinessCardModel>
  <BusinessCardModel>
    <FirstName>Cody</FirstName>
    <LastName>Frances Best</LastName>
    <Position>Orci Ut Industries</Position>
    <BossId>0</BossId>
    <Id>100</Id>
  </BusinessCardModel>
  <BusinessCardModel>
    <FirstName>Ira</FirstName>
    <LastName>Chava Miller</LastName>
    <Position>Ullamcorper Velit Incorporated</Position>
    <BossId>0</BossId>
    <Id>101</Id>
  </BusinessCardModel>
  <BusinessCardModel>
    <FirstName>Martin</FirstName>
    <LastName>Venus Sargent</LastName>
    <Position>Sed Eu Nibh Company</Position>
    <BossId>0</BossId>
    <Id>102</Id>
  </BusinessCardModel>
  <BusinessCardModel>
    <FirstName>Roth</FirstName>
    <LastName>Reagan Padilla</LastName>
    <Position>Orci Adipiscing Non Foundation</Position>
    <BossId>0</BossId>
    <Id>103</Id>
  </BusinessCardModel>
  <BusinessCardModel>
    <FirstName>Berk</FirstName>
    <LastName>Quinn Pace</LastName>
    <Position>Euismod Et Ltd</Position>
    <BossId>0</BossId>
    <Id>104</Id>
  </BusinessCardModel>
  <BusinessCardModel>
    <FirstName>Sean</FirstName>
    <LastName>Clementine Copeland</LastName>
    <Position>Fringilla Incorporated</Position>
    <BossId>0</BossId>
    <Id>105</Id>
  </BusinessCardModel>
  <BusinessCardModel>
    <FirstName>Giacomo</FirstName>
    <LastName>Isadora Mays</LastName>
    <Position>Mus Proin Inc.</Position>
    <BossId>0</BossId>
    <Id>106</Id>
  </BusinessCardModel>
  <BusinessCardModel>
    <FirstName>Berk</FirstName>
    <LastName>Madaline Marshall</LastName>
    <Position>Suspendisse Aliquet Sem LLC</Position>
    <BossId>0</BossId>
    <Id>107</Id>
  </BusinessCardModel>
  <BusinessCardModel>
    <FirstName>Beau</FirstName>
    <LastName>Amela Dixon</LastName>
    <Position>Felis Company</Position>
    <BossId>0</BossId>
    <Id>108</Id>
  </BusinessCardModel>
  <BusinessCardModel>
    <FirstName>Dylan</FirstName>
    <LastName>Fatima Warren</LastName>
    <Position>Dolor Donec Limited</Position>
    <BossId>0</BossId>
    <Id>109</Id>
  </BusinessCardModel>
  <BusinessCardModel>
    <FirstName>Nasim</FirstName>
    <LastName>Chiquita Berry</LastName>
    <Position>Maecenas Company</Position>
    <BossId>0</BossId>
    <Id>110</Id>
  </BusinessCardModel>
  <BusinessCardModel>
    <FirstName>Xanthus</FirstName>
    <LastName>Quemby Woodward</LastName>
    <Position>Cum Sociis Natoque PC</Position>
    <BossId>0</BossId>
    <Id>111</Id>
  </BusinessCardModel>
  <BusinessCardModel>
    <FirstName>Beck</FirstName>
    <LastName>Hollee Whitfield</LastName>
    <Position>Orci Inc.</Position>
    <BossId>0</BossId>
    <Id>112</Id>
  </BusinessCardModel>
  <BusinessCardModel>
    <FirstName>Cyrus</FirstName>
    <LastName>Zelenia Garrett</LastName>
    <Position>Interdum Limited</Position>
    <BossId>0</BossId>
    <Id>113</Id>
  </BusinessCardModel>
  <BusinessCardModel>
    <FirstName>Tucker</FirstName>
    <LastName>Joan Clemons</LastName>
    <Position>Orci Luctus Company</Position>
    <BossId>0</BossId>
    <Id>114</Id>
  </BusinessCardModel>
  <BusinessCardModel>
    <FirstName>Mark</FirstName>
    <LastName>Mollie Carver</LastName>
    <Position>Condimentum Eget Consulting</Position>
    <BossId>0</BossId>
    <Id>115</Id>
  </BusinessCardModel>
  <BusinessCardModel>
    <FirstName>Norman</FirstName>
    <LastName>Zoe Lynch</LastName>
    <Position>Nam Interdum Consulting</Position>
    <BossId>0</BossId>
    <Id>116</Id>
  </BusinessCardModel>
  <BusinessCardModel>
    <FirstName>Leonard</FirstName>
    <LastName>September Carpenter</LastName>
    <Position>Duis Dignissim Tempor Company</Position>
    <BossId>0</BossId>
    <Id>117</Id>
  </BusinessCardModel>
  <BusinessCardModel>
    <FirstName>Dustin</FirstName>
    <LastName>Cassady Wilkins</LastName>
    <Position>Erat Vivamus Nisi PC</Position>
    <BossId>0</BossId>
    <Id>118</Id>
  </BusinessCardModel>
  <BusinessCardModel>
    <FirstName>Bruno</FirstName>
    <LastName>Tallulah Alvarado</LastName>
    <Position>Elit Dictum Eu Company</Position>
    <BossId>0</BossId>
    <Id>119</Id>
  </BusinessCardModel>
  <BusinessCardModel>
    <FirstName>Isaac</FirstName>
    <LastName>Lacey Merritt</LastName>
    <Position>A Neque Nullam Corp.</Position>
    <BossId>0</BossId>
    <Id>120</Id>
  </BusinessCardModel>
  <BusinessCardModel>
    <FirstName>Upton</FirstName>
    <LastName>Shellie Mcfadden</LastName>
    <Position>Phasellus Nulla Integer Incorporated</Position>
    <BossId>0</BossId>
    <Id>121</Id>
  </BusinessCardModel>
  <BusinessCardModel>
    <FirstName>Dexter</FirstName>
    <LastName>Jasmine Levine</LastName>
    <Position>Justo Eu Institute</Position>
    <BossId>0</BossId>
    <Id>122</Id>
  </BusinessCardModel>
  <BusinessCardModel>
    <FirstName>Graham</FirstName>
    <LastName>Ignacia Hudson</LastName>
    <Position>Urna Ut Tincidunt LLC</Position>
    <BossId>0</BossId>
    <Id>123</Id>
  </BusinessCardModel>
  <BusinessCardModel>
    <FirstName>Daniel</FirstName>
    <LastName>Shaeleigh Collier</LastName>
    <Position>Elit Incorporated</Position>
    <BossId>0</BossId>
    <Id>124</Id>
  </BusinessCardModel>
  <BusinessCardModel>
    <FirstName>Colby</FirstName>
    <LastName>Caryn Kim</LastName>
    <Position>Ipsum Dolor Limited</Position>
    <BossId>0</BossId>
    <Id>125</Id>
  </BusinessCardModel>
  <BusinessCardModel>
    <FirstName>Dillon</FirstName>
    <LastName>Emerald Holt</LastName>
    <Position>Mauris A Limited</Position>
    <BossId>0</BossId>
    <Id>126</Id>
  </BusinessCardModel>
  <BusinessCardModel>
    <FirstName>Kirk</FirstName>
    <LastName>Meredith Torres</LastName>
    <Position>Urna Nec LLP</Position>
    <BossId>0</BossId>
    <Id>127</Id>
  </BusinessCardModel>
  <BusinessCardModel>
    <FirstName>Chadwick</FirstName>
    <LastName>Blythe Bradford</LastName>
    <Position>Vel Institute</Position>
    <BossId>0</BossId>
    <Id>128</Id>
  </BusinessCardModel>
  <BusinessCardModel>
    <FirstName>Cole</FirstName>
    <LastName>Celeste Munoz</LastName>
    <Position>At Nisi Cum LLP</Position>
    <BossId>0</BossId>
    <Id>129</Id>
  </BusinessCardModel>
  <BusinessCardModel>
    <FirstName>Ulric</FirstName>
    <LastName>Grace Soto</LastName>
    <Position>Sit PC</Position>
    <BossId>0</BossId>
    <Id>130</Id>
  </BusinessCardModel>
  <BusinessCardModel>
    <FirstName>Channing</FirstName>
    <LastName>Holly Silva</LastName>
    <Position>Tempus Scelerisque Consulting</Position>
    <BossId>0</BossId>
    <Id>131</Id>
  </BusinessCardModel>
  <BusinessCardModel>
    <FirstName>Scott</FirstName>
    <LastName>Daria Ward</LastName>
    <Position>Porttitor Consulting</Position>
    <BossId>0</BossId>
    <Id>132</Id>
  </BusinessCardModel>
  <BusinessCardModel>
    <FirstName>Odysseus</FirstName>
    <LastName>Kathleen Odonnell</LastName>
    <Position>Lacinia Vitae Sodales PC</Position>
    <BossId>0</BossId>
    <Id>133</Id>
  </BusinessCardModel>
  <BusinessCardModel>
    <FirstName>Craig</FirstName>
    <LastName>Victoria Peterson</LastName>
    <Position>Amet Risus Company</Position>
    <BossId>0</BossId>
    <Id>134</Id>
  </BusinessCardModel>
  <BusinessCardModel>
    <FirstName>Todd</FirstName>
    <LastName>Amity Adkins</LastName>
    <Position>Odio A Foundation</Position>
    <BossId>0</BossId>
    <Id>135</Id>
  </BusinessCardModel>
  <BusinessCardModel>
    <FirstName>Nero</FirstName>
    <LastName>Josephine Raymond</LastName>
    <Position>Aenean Egestas Company</Position>
    <BossId>0</BossId>
    <Id>136</Id>
  </BusinessCardModel>
  <BusinessCardModel>
    <FirstName>Allen</FirstName>
    <LastName>Desirae Rocha</LastName>
    <Position>Sed Dictum Proin Incorporated</Position>
    <BossId>0</BossId>
    <Id>137</Id>
  </BusinessCardModel>
  <BusinessCardModel>
    <FirstName>Theodore</FirstName>
    <LastName>Aurora Collier</LastName>
    <Position>Laoreet Lectus Quis Ltd</Position>
    <BossId>0</BossId>
    <Id>138</Id>
  </BusinessCardModel>
  <BusinessCardModel>
    <FirstName>Merritt</FirstName>
    <LastName>Britanney Lester</LastName>
    <Position>Risus Morbi Ltd</Position>
    <BossId>0</BossId>
    <Id>139</Id>
  </BusinessCardModel>
  <BusinessCardModel>
    <FirstName>Nathan</FirstName>
    <LastName>Evangeline Blake</LastName>
    <Position>Nec Tellus LLC</Position>
    <BossId>0</BossId>
    <Id>140</Id>
  </BusinessCardModel>
  <BusinessCardModel>
    <FirstName>Marshall</FirstName>
    <LastName>Uta Hunt</LastName>
    <Position>Id Erat Associates</Position>
    <BossId>0</BossId>
    <Id>141</Id>
  </BusinessCardModel>
  <BusinessCardModel>
    <FirstName>Guy</FirstName>
    <LastName>Suki Webb</LastName>
    <Position>Penatibus Et LLC</Position>
    <BossId>0</BossId>
    <Id>142</Id>
  </BusinessCardModel>
  <BusinessCardModel>
    <FirstName>Jameson</FirstName>
    <LastName>Isadora Delacruz</LastName>
    <Position>Quam Inc.</Position>
    <BossId>0</BossId>
    <Id>143</Id>
  </BusinessCardModel>
  <BusinessCardModel>
    <FirstName>Ian</FirstName>
    <LastName>Leah Townsend</LastName>
    <Position>Sed Id Institute</Position>
    <BossId>0</BossId>
    <Id>144</Id>
  </BusinessCardModel>
  <BusinessCardModel>
    <FirstName>Deacon</FirstName>
    <LastName>Kendall Contreras</LastName>
    <Position>Molestie Orci Tincidunt Foundation</Position>
    <BossId>0</BossId>
    <Id>145</Id>
  </BusinessCardModel>
  <BusinessCardModel>
    <FirstName>Hammett</FirstName>
    <LastName>Brenda Wells</LastName>
    <Position>Lectus Corp.</Position>
    <BossId>0</BossId>
    <Id>146</Id>
  </BusinessCardModel>
  <BusinessCardModel>
    <FirstName>Ferdinand</FirstName>
    <LastName>Iris Randolph</LastName>
    <Position>Eu Turpis Nulla Incorporated</Position>
    <BossId>0</BossId>
    <Id>147</Id>
  </BusinessCardModel>
  <BusinessCardModel>
    <FirstName>Graiden</FirstName>
    <LastName>Madeson Wallace</LastName>
    <Position>Lorem Eu Inc.</Position>
    <BossId>0</BossId>
    <Id>148</Id>
  </BusinessCardModel>
  <BusinessCardModel>
    <FirstName>Tobias</FirstName>
    <LastName>Chanda Mclean</LastName>
    <Position>Nec Tempus Consulting</Position>
    <BossId>0</BossId>
    <Id>149</Id>
  </BusinessCardModel>
  <BusinessCardModel>
    <FirstName>Beck</FirstName>
    <LastName>Blaine May</LastName>
    <Position>Enim Etiam PC</Position>
    <BossId>0</BossId>
    <Id>150</Id>
  </BusinessCardModel>
  <BusinessCardModel>
    <FirstName>Brady</FirstName>
    <LastName>Kai Tran</LastName>
    <Position>Curabitur Egestas Nunc LLC</Position>
    <BossId>0</BossId>
    <Id>151</Id>
  </BusinessCardModel>
  <BusinessCardModel>
    <FirstName>Kermit</FirstName>
    <LastName>Kathleen Ward</LastName>
    <Position>Convallis Est Vitae Limited</Position>
    <BossId>0</BossId>
    <Id>152</Id>
  </BusinessCardModel>
  <BusinessCardModel>
    <FirstName>Declan</FirstName>
    <LastName>Ima Key</LastName>
    <Position>Nam Corp.</Position>
    <BossId>0</BossId>
    <Id>153</Id>
  </BusinessCardModel>
  <BusinessCardModel>
    <FirstName>Derek</FirstName>
    <LastName>Mara Valentine</LastName>
    <Position>Penatibus Inc.</Position>
    <BossId>0</BossId>
    <Id>154</Id>
  </BusinessCardModel>
  <BusinessCardModel>
    <FirstName>Cole</FirstName>
    <LastName>Reagan Kirk</LastName>
    <Position>Ridiculus LLP</Position>
    <BossId>0</BossId>
    <Id>155</Id>
  </BusinessCardModel>
  <BusinessCardModel>
    <FirstName>Cade</FirstName>
    <LastName>Jane Dunn</LastName>
    <Position>In Condimentum Donec Limited</Position>
    <BossId>0</BossId>
    <Id>156</Id>
  </BusinessCardModel>
  <BusinessCardModel>
    <FirstName>Clark</FirstName>
    <LastName>Ella Shepherd</LastName>
    <Position>A Auctor Industries</Position>
    <BossId>0</BossId>
    <Id>157</Id>
  </BusinessCardModel>
  <BusinessCardModel>
    <FirstName>Laith</FirstName>
    <LastName>Deborah Whitehead</LastName>
    <Position>Quam Curabitur Vel LLP</Position>
    <BossId>0</BossId>
    <Id>158</Id>
  </BusinessCardModel>
  <BusinessCardModel>
    <FirstName>Hu</FirstName>
    <LastName>Quin Emerson</LastName>
    <Position>Lobortis Quis Incorporated</Position>
    <BossId>0</BossId>
    <Id>159</Id>
  </BusinessCardModel>
  <BusinessCardModel>
    <FirstName>Hakeem</FirstName>
    <LastName>Maryam Mcdaniel</LastName>
    <Position>Id Ante Corporation</Position>
    <BossId>0</BossId>
    <Id>160</Id>
  </BusinessCardModel>
  <BusinessCardModel>
    <FirstName>Jarrod</FirstName>
    <LastName>Hilary Short</LastName>
    <Position>Quisque Varius Nam PC</Position>
    <BossId>0</BossId>
    <Id>161</Id>
  </BusinessCardModel>
  <BusinessCardModel>
    <FirstName>Norman</FirstName>
    <LastName>Mikayla Shaw</LastName>
    <Position>Donec Fringilla Corp.</Position>
    <BossId>0</BossId>
    <Id>162</Id>
  </BusinessCardModel>
  <BusinessCardModel>
    <FirstName>Price</FirstName>
    <LastName>Jasmine Romero</LastName>
    <Position>In Consequat Incorporated</Position>
    <BossId>0</BossId>
    <Id>163</Id>
  </BusinessCardModel>
  <BusinessCardModel>
    <FirstName>Keegan</FirstName>
    <LastName>Glenna Tucker</LastName>
    <Position>Elit Curabitur Ltd</Position>
    <BossId>0</BossId>
    <Id>164</Id>
  </BusinessCardModel>
  <BusinessCardModel>
    <FirstName>Boris</FirstName>
    <LastName>Kendall Woodward</LastName>
    <Position>Nec Urna Et Limited</Position>
    <BossId>0</BossId>
    <Id>165</Id>
  </BusinessCardModel>
  <BusinessCardModel>
    <FirstName>Bernard</FirstName>
    <LastName>Sage Richard</LastName>
    <Position>Sed Industries</Position>
    <BossId>0</BossId>
    <Id>166</Id>
  </BusinessCardModel>
  <BusinessCardModel>
    <FirstName>Keefe</FirstName>
    <LastName>Charissa Green</LastName>
    <Position>Ut Nisi A Corp.</Position>
    <BossId>0</BossId>
    <Id>167</Id>
  </BusinessCardModel>
  <BusinessCardModel>
    <FirstName>Grant</FirstName>
    <LastName>Brooke Duncan</LastName>
    <Position>Dapibus Foundation</Position>
    <BossId>0</BossId>
    <Id>168</Id>
  </BusinessCardModel>
  <BusinessCardModel>
    <FirstName>Amos</FirstName>
    <LastName>Indigo Fitzpatrick</LastName>
    <Position>Neque Sed Company</Position>
    <BossId>0</BossId>
    <Id>169</Id>
  </BusinessCardModel>
  <BusinessCardModel>
    <FirstName>Eagan</FirstName>
    <LastName>Ignacia Chase</LastName>
    <Position>Ultricies Dignissim Lacus Limited</Position>
    <BossId>0</BossId>
    <Id>170</Id>
  </BusinessCardModel>
  <BusinessCardModel>
    <FirstName>Porter</FirstName>
    <LastName>Ariel Sparks</LastName>
    <Position>Lorem Fringilla Associates</Position>
    <BossId>0</BossId>
    <Id>171</Id>
  </BusinessCardModel>
  <BusinessCardModel>
    <FirstName>Ralph</FirstName>
    <LastName>Deanna Dale</LastName>
    <Position>Elit Aliquam Ltd</Position>
    <BossId>0</BossId>
    <Id>172</Id>
  </BusinessCardModel>
  <BusinessCardModel>
    <FirstName>Clarke</FirstName>
    <LastName>Winter Webb</LastName>
    <Position>Nam Tempor Diam Ltd</Position>
    <BossId>0</BossId>
    <Id>173</Id>
  </BusinessCardModel>
  <BusinessCardModel>
    <FirstName>Knox</FirstName>
    <LastName>Dara Holt</LastName>
    <Position>Non Consulting</Position>
    <BossId>0</BossId>
    <Id>174</Id>
  </BusinessCardModel>
  <BusinessCardModel>
    <FirstName>Zephania</FirstName>
    <LastName>Raven Soto</LastName>
    <Position>Aliquam Erat Company</Position>
    <BossId>0</BossId>
    <Id>175</Id>
  </BusinessCardModel>
  <BusinessCardModel>
    <FirstName>Scott</FirstName>
    <LastName>Ora Sawyer</LastName>
    <Position>Velit Eget Laoreet Industries</Position>
    <BossId>0</BossId>
    <Id>176</Id>
  </BusinessCardModel>
  <BusinessCardModel>
    <FirstName>Malcolm</FirstName>
    <LastName>Grace Joseph</LastName>
    <Position>Ipsum Non Arcu LLC</Position>
    <BossId>0</BossId>
    <Id>177</Id>
  </BusinessCardModel>
  <BusinessCardModel>
    <FirstName>Kareem</FirstName>
    <LastName>Morgan Richards</LastName>
    <Position>Nec Tempus Foundation</Position>
    <BossId>0</BossId>
    <Id>178</Id>
  </BusinessCardModel>
  <BusinessCardModel>
    <FirstName>Avram</FirstName>
    <LastName>Remedios Stout</LastName>
    <Position>Sem Associates</Position>
    <BossId>0</BossId>
    <Id>179</Id>
  </BusinessCardModel>
  <BusinessCardModel>
    <FirstName>Laith</FirstName>
    <LastName>Minerva William</LastName>
    <Position>Blandit Mattis Inc.</Position>
    <BossId>0</BossId>
    <Id>180</Id>
  </BusinessCardModel>
  <BusinessCardModel>
    <FirstName>Otto</FirstName>
    <LastName>Bianca Franklin</LastName>
    <Position>Diam Corporation</Position>
    <BossId>0</BossId>
    <Id>181</Id>
  </BusinessCardModel>
  <BusinessCardModel>
    <FirstName>Hiram</FirstName>
    <LastName>Ocean Lee</LastName>
    <Position>Non Arcu Ltd</Position>
    <BossId>0</BossId>
    <Id>182</Id>
  </BusinessCardModel>
  <BusinessCardModel>
    <FirstName>Oren</FirstName>
    <LastName>Hedda Banks</LastName>
    <Position>Suspendisse Company</Position>
    <BossId>0</BossId>
    <Id>183</Id>
  </BusinessCardModel>
  <BusinessCardModel>
    <FirstName>Tanner</FirstName>
    <LastName>Zenaida Chavez</LastName>
    <Position>Aenean Sed Pede LLP</Position>
    <BossId>0</BossId>
    <Id>184</Id>
  </BusinessCardModel>
  <BusinessCardModel>
    <FirstName>Hyatt</FirstName>
    <LastName>Kirby Morris</LastName>
    <Position>Donec PC</Position>
    <BossId>0</BossId>
    <Id>185</Id>
  </BusinessCardModel>
  <BusinessCardModel>
    <FirstName>Moses</FirstName>
    <LastName>Calista Dalton</LastName>
    <Position>Ac Fermentum Vel Associates</Position>
    <BossId>0</BossId>
    <Id>186</Id>
  </BusinessCardModel>
  <BusinessCardModel>
    <FirstName>Isaac</FirstName>
    <LastName>Regan Trujillo</LastName>
    <Position>Sit Amet Luctus Incorporated</Position>
    <BossId>0</BossId>
    <Id>187</Id>
  </BusinessCardModel>
  <BusinessCardModel>
    <FirstName>Arsenio</FirstName>
    <LastName>Sigourney Pugh</LastName>
    <Position>Fermentum Fermentum Arcu Associates</Position>
    <BossId>0</BossId>
    <Id>188</Id>
  </BusinessCardModel>
  <BusinessCardModel>
    <FirstName>Harrison</FirstName>
    <LastName>Signe Dickerson</LastName>
    <Position>Cum Incorporated</Position>
    <BossId>0</BossId>
    <Id>189</Id>
  </BusinessCardModel>
  <BusinessCardModel>
    <FirstName>Alec</FirstName>
    <LastName>Echo Welch</LastName>
    <Position>Orci LLC</Position>
    <BossId>0</BossId>
    <Id>190</Id>
  </BusinessCardModel>
  <BusinessCardModel>
    <FirstName>Moses</FirstName>
    <LastName>Bethany Ratliff</LastName>
    <Position>Mollis Inc.</Position>
    <BossId>0</BossId>
    <Id>191</Id>
  </BusinessCardModel>
  <BusinessCardModel>
    <FirstName>Erich</FirstName>
    <LastName>Darrel Mercer</LastName>
    <Position>Justo PC</Position>
    <BossId>0</BossId>
    <Id>192</Id>
  </BusinessCardModel>
  <BusinessCardModel>
    <FirstName>Derek</FirstName>
    <LastName>Jessica Cabrera</LastName>
    <Position>Phasellus Associates</Position>
    <BossId>0</BossId>
    <Id>193</Id>
  </BusinessCardModel>
  <BusinessCardModel>
    <FirstName>Victor</FirstName>
    <LastName>Amy Clayton</LastName>
    <Position>Sed Hendrerit A Foundation</Position>
    <BossId>0</BossId>
    <Id>194</Id>
  </BusinessCardModel>
  <BusinessCardModel>
    <FirstName>Bradley</FirstName>
    <LastName>Kaden Humphrey</LastName>
    <Position>Viverra Donec LLC</Position>
    <BossId>0</BossId>
    <Id>195</Id>
  </BusinessCardModel>
  <BusinessCardModel>
    <FirstName>Karīnā</FirstName>
    <LastName>Kaye Hoffman</LastName>
    <Position>Augue Eu Tempor Ltd</Position>
    <BossId>0</BossId>
    <Id>196</Id>
  </BusinessCardModel>
  <BusinessCardModel>
    <FirstName>Abbot</FirstName>
    <LastName>Aubrey Kline</LastName>
    <Position>Ipsum Cursus PC</Position>
    <Department>Dep</Department>
    <BossId>45</BossId>
    <Id>197</Id>
    <Email>sasdf@cp.com</Email>
  </BusinessCardModel>
  <BusinessCardModel>
    <FirstName>Julian</FirstName>
    <LastName>Shafira Jefferson</LastName>
    <Position>Non Massa Non Company</Position>
    <BossId>0</BossId>
    <Id>198</Id>
  </BusinessCardModel>
  <BusinessCardModel>
    <FirstName>Jamal</FirstName>
    <LastName>Ursula Allen</LastName>
    <Position>Id LLC</Position>
    <BossId>0</BossId>
    <Id>199</Id>
  </BusinessCardModel>
  <BusinessCardModel>
    <FirstName>Kenneth</FirstName>
    <LastName>Lillian Bailey</LastName>
    <Position>Vivamus Limited</Position>
    <BossId>0</BossId>
    <Id>200</Id>
  </BusinessCardModel>
  <BusinessCardModel>
    <FirstName>aa</FirstName>
    <LastName>bbb</LastName>
    <BossId>122</BossId>
    <Id>201</Id>
  </BusinessCardModel>
  <BusinessCardModel>
    <FirstName>bbb</FirstName>
    <LastName>ccc</LastName>
    <BossId>0</BossId>
    <Id>202</Id>
  </BusinessCardModel>
  <BusinessCardModel>
    <FirstName>ccc</FirstName>
    <LastName>dd</LastName>
    <BossId>0</BossId>
    <Id>203</Id>
  </BusinessCardModel>
  <BusinessCardModel>
    <FirstName>qq</FirstName>
    <LastName>ww</LastName>
    <BossId>0</BossId>
    <Id>204</Id>
  </BusinessCardModel>
  <BusinessCardModel>
    <FirstName>andfasdf</FirstName>
    <LastName>asdf</LastName>
    <BossId>0</BossId>
    <Id>205</Id>
  </BusinessCardModel>
  <BusinessCardModel>
    <FirstName>u</FirstName>
    <LastName>u</LastName>
    <BossId>0</BossId>
    <Id>206</Id>
  </BusinessCardModel>
  <BusinessCardModel>
    <FirstName>yy</FirstName>
    <LastName>yy</LastName>
    <BossId>0</BossId>
    <Id>207</Id>
  </BusinessCardModel>
  <BusinessCardModel>
    <FirstName>qq</FirstName>
    <LastName>qq</LastName>
    <BossId>121</BossId>
    <Id>208</Id>
  </BusinessCardModel>
  <BusinessCardModel>
    <FirstName>ww</FirstName>
    <LastName>ww</LastName>
    <BossId xsi:nil="true" />
    <Id>209</Id>
  </BusinessCardModel>
  <BusinessCardModel>
    <FirstName>eee</FirstName>
    <LastName>eee</LastName>
    <BossId>146</BossId>
    <Id>210</Id>
  </BusinessCardModel>
</ArrayOfBusinessCardModel>